mb_solana/__init__.py
mb_solana/block.py
mb_solana/helpers.py
mb_solana/solana_account.py
mb_solana/solana_cli.py
mb_solana/solana_rpc.py
mb_solana/spl_token.py
mb_solana/cli/__init__.py
mb_solana/cli/helpers.py
mb_solana/cli/cmd/balance_cmd.py
mb_solana/cli/cmd/example_cmd.py
mb_solana/cli/cmd/generate_accounts_cmd.py
mb_solana/cli/cmd/keypair_cmd.py
mb_solana/cli/cmd/transfer_sol_cmd.py
mb_solana/cli/examples/balance.yml
mb_solana/cli/examples/transfer-sol.yml
mb_solana-0.5.12.dist-info/METADATA
mb_solana-0.5.12.dist-info/WHEEL
mb_solana-0.5.12.dist-info/entry_points.txt
mb_solana-0.5.12.dist-info/top_level.txt
mb_solana-0.5.12.dist-info/RECORD
