Metadata-Version: 2.1
Name: mb-solana
Version: 0.5.12
Requires-Python: >=3.10
Requires-Dist: click (==8.1.2)
Requires-Dist: click-aliases (==1.0.1)
Requires-Dist: PyYAML (==5.4.1)
Requires-Dist: Jinja2
Requires-Dist: base58
Requires-Dist: toml (==0.10.2)
Requires-Dist: solana (==0.23.3)
Requires-Dist: mb-std (~=0.4)
Provides-Extra: dev
Requires-Dist: pytest (==7.1.2) ; extra == 'dev'
Requires-Dist: pytest-xdist (==2.5.0) ; extra == 'dev'
Requires-Dist: pre-commit (==2.19.0) ; extra == 'dev'
Requires-Dist: wheel (==0.37.1) ; extra == 'dev'
Requires-Dist: twine (==4.0.0) ; extra == 'dev'
Requires-Dist: pip-audit (==2.3.1) ; extra == 'dev'
